fashionpedia/__init__.py
fashionpedia/fp.py
fashionpedia/fp_eval.py
fashionpedia-1.1.dist-info/METADATA
fashionpedia-1.1.dist-info/WHEEL
fashionpedia-1.1.dist-info/top_level.txt
fashionpedia-1.1.dist-info/RECORD
