Metadata-Version: 2.1
Name: fashionpedia
Version: 1.1
Summary: Python API for Fashionpedia dataset.
Home-page: https://github.com/KMnP/fashionpedia-api
Author: Menglin Jia
Author-email: mj493@cornell.edu
License: UNKNOWN
Platform: UNKNOWN
Requires-Python: >=3.6
